kafklient/__init__.py
kafklient/cli.py
kafklient/clients/__init__.py
kafklient/clients/base_client.py
kafklient/clients/listener.py
kafklient/clients/rpc.py
kafklient/mcp/__init__.py
kafklient/mcp/_config.py
kafklient/mcp/_utils.py
kafklient/mcp/client.py
kafklient/mcp/server.py
kafklient/mcp/session.py
kafklient/py.typed
kafklient/types/__init__.py
kafklient/types/backend.py
kafklient/types/config.py
kafklient/types/parser.py
kafklient/utils/__init__.py
kafklient/utils/broadcaster.py
kafklient/utils/executor.py
kafklient/utils/task.py
kafklient-0.5.2.dist-info/WHEEL
kafklient-0.5.2.dist-info/entry_points.txt
kafklient-0.5.2.dist-info/METADATA
kafklient-0.5.2.dist-info/RECORD
