Metadata-Version: 2.3
Name: kafklient
Version: 0.5.2
Summary: Async Kafka helpers built on confluent_kafka.
Requires-Dist: confluent-kafka>=2.13.0
Requires-Dist: pydantic>=2.12.5
Requires-Dist: typer>=0.20.1
Requires-Dist: kafklient[dev] ; extra == 'all'
Requires-Dist: kafklient[mcp] ; extra == 'all'
Requires-Dist: pyright>=1.1.408 ; extra == 'dev'
Requires-Dist: ruff>=0.14.7 ; extra == 'dev'
Requires-Dist: fastmcp>=2.14.1,<3 ; extra == 'mcp'
Requires-Python: >=3.12
Provides-Extra: all
Provides-Extra: dev
Provides-Extra: mcp
